setup.py
wlx123456789/__init__.py
wlx123456789/demo1.py
wlx123456789/demo2.py
wlx123456789.egg-info/PKG-INFO
wlx123456789.egg-info/SOURCES.txt
wlx123456789.egg-info/dependency_links.txt
wlx123456789.egg-info/top_level.txt